alfred3_scheduler/__init__.py
alfred3_scheduler/_version.py
alfred3_scheduler/element.py
alfred3_scheduler/page.py
alfred3_scheduler/scheduler.py
alfred3_scheduler/section.py
alfred3_scheduler/text.py
alfred3_scheduler/static/__init__.py
alfred3_scheduler/static/de.json
alfred3_scheduler/static/en.json
alfred3_scheduler/templates/html/AddDateSlot.html.j2
alfred3_scheduler/templates/html/DateSlotRegistration.html.j2
alfred3_scheduler/templates/html/DateSlots.html.j2
alfred3_scheduler/templates/html/DeleteSlotButton.html.j2
alfred3_scheduler/templates/html/SendMailButton.html.j2
alfred3_scheduler/templates/html/ShowParticipantsButton.html.j2
alfred3_scheduler/templates/html/ViewDateSlots.html.j2
alfred3_scheduler/templates/html/cancel_slot.html.j2
alfred3_scheduler/templates/html/confirm_registration_de.html.j2
alfred3_scheduler/templates/html/remind_participants.html.j2
alfred3_scheduler/templates/js/add_date_slot.js.j2
alfred3_scheduler/templates/js/dateslot_registration.js.j2
alfred3_scheduler/templates/js/send_mail_button.js.j2
alfred3_scheduler/templates/js/view_date_slots.js.j2
alfred3_scheduler-0.1.0a1.dist-info/LICENSE
alfred3_scheduler-0.1.0a1.dist-info/METADATA
alfred3_scheduler-0.1.0a1.dist-info/WHEEL
alfred3_scheduler-0.1.0a1.dist-info/top_level.txt
alfred3_scheduler-0.1.0a1.dist-info/RECORD
